requests-lite/__init__.py
requests-lite/__version__.py
requests-lite/_internal_utils.py
requests-lite/adapters.py
requests-lite/api.py
requests-lite/auth.py
requests-lite/certs.py
requests-lite/compat.py
requests-lite/cookies.py
requests-lite/exceptions.py
requests-lite/help.py
requests-lite/hooks.py
requests-lite/models.py
requests-lite/packages.py
requests-lite/sessions.py
requests-lite/status_codes.py
requests-lite/structures.py
requests-lite/utils.py
requests_lite/__init__.py
requests_lite/__version__.py
requests_lite/_internal_utils.py
requests_lite/adapters.py
requests_lite/api.py
requests_lite/auth.py
requests_lite/certs.py
requests_lite/compat.py
requests_lite/cookies.py
requests_lite/exceptions.py
requests_lite/help.py
requests_lite/hooks.py
requests_lite/models.py
requests_lite/packages.py
requests_lite/sessions.py
requests_lite/status_codes.py
requests_lite/structures.py
requests_lite/utils.py
requests_lite-2.32.7.dist-info/LICENSE
requests_lite-2.32.7.dist-info/METADATA
requests_lite-2.32.7.dist-info/WHEEL
requests_lite-2.32.7.dist-info/top_level.txt
requests_lite-2.32.7.dist-info/RECORD
